pybar_fei4_interpreter/AnalysisFunctions.h
pybar_fei4_interpreter/Basis.cpp
pybar_fei4_interpreter/Basis.h
pybar_fei4_interpreter/Histogram.cpp
pybar_fei4_interpreter/Histogram.h
pybar_fei4_interpreter/Interpret.cpp
pybar_fei4_interpreter/Interpret.h
pybar_fei4_interpreter/__init__.py
pybar_fei4_interpreter/analysis_functions.cp37-win32.pyd
pybar_fei4_interpreter/analysis_functions.cpp
pybar_fei4_interpreter/analysis_functions.pyx
pybar_fei4_interpreter/analysis_utils.py
pybar_fei4_interpreter/data_histograming.cp37-win32.pyd
pybar_fei4_interpreter/data_histograming.cpp
pybar_fei4_interpreter/data_histograming.pyx
pybar_fei4_interpreter/data_interpreter.cp37-win32.pyd
pybar_fei4_interpreter/data_interpreter.cpp
pybar_fei4_interpreter/data_interpreter.pyx
pybar_fei4_interpreter/data_struct.pxd
pybar_fei4_interpreter/data_struct.py
pybar_fei4_interpreter/defines.h
pybar_fei4_interpreter/external/changelog.txt
pybar_fei4_interpreter/external/inttypes.h
pybar_fei4_interpreter/external/stdint.h
pybar_fei4_interpreter/testing/test_analysis.py
pybar_fei4_interpreter/testing/test_analysis_data/hist_data.h5
pyBAR_fei4_interpreter-1.5.1.dist-info/LICENSE
pyBAR_fei4_interpreter-1.5.1.dist-info/METADATA
pyBAR_fei4_interpreter-1.5.1.dist-info/WHEEL
pyBAR_fei4_interpreter-1.5.1.dist-info/top_level.txt
pyBAR_fei4_interpreter-1.5.1.dist-info/RECORD
