Metadata-Version: 1.2
Name: pyBAR_fei4_interpreter
Version: 1.5.1
Summary: pyBAR_fei4_interpreter - Fast ATLAS FE-I4 raw data interpreter for pyBAR
Home-page: https://github.com/SiLab-Bonn/pyBAR_fei4_interpreter
Author: Jens Janssen, David-Leon Pohl
Author-email: janssen@physik.uni-bonn.de, pohl@physik.uni-bonn.de
Maintainer: Jens Janssen, David-Leon Pohl
Maintainer-email: janssen@physik.uni-bonn.de, pohl@physik.uni-bonn.de
License: BSD 3-Clause ("BSD New" or "BSD Simplified") License
Platform: any
Requires-Python: >=2.7
